vigo/__init__.py
vigo/__main__.py
vigo/bootstrap.py
vigo/cli.py
vigo/common.py
vigo/config.py
vigo/exceptions.py
vigo/git.py
vigo/github.py
vigo/governance.py
vigo/models.py
vigo/templates/cli.txt
vigo/templates/cli/classes.txt
vigo/templates/cli/imports.txt
vigo/tests/test_cli.py
vigo/tests/test_common.py
vigo-0.1.0.dist-info/AUTHORS
vigo-0.1.0.dist-info/METADATA
vigo-0.1.0.dist-info/WHEEL
vigo-0.1.0.dist-info/entry_points.txt
vigo-0.1.0.dist-info/pbr.json
vigo-0.1.0.dist-info/top_level.txt
vigo-0.1.0.dist-info/RECORD
