Metadata-Version: 2.1
Name: vigo
Version: 0.1.0
Summary: Find code and files on openstack projects
Home-page: https://github.com/4383/vigo/
Author: Hervé Beraud
Author-email: herveberaud.pro@gmail.com
License: MIT
Platform: UNKNOWN
Classifier: Development Status :: 5 - Production/Stable
Classifier: Intended Audience :: Information Technology
Classifier: License :: OSI Approved :: MIT License
Classifier: Operating System :: POSIX
Classifier: Programming Language :: Python
Classifier: Programming Language :: Python :: 3
Classifier: Programming Language :: Python :: 3.5
Classifier: Programming Language :: Python :: 3.6
Classifier: Programming Language :: Python :: 3.7
Requires-Dist: PyYAML
Requires-Dist: requests
Provides-Extra: tests
Requires-Dist: tox ; extra == 'tests'
